nexus_finance/__init__.py
nexus_finance/__main__.py
nexus_finance/app.py
nexus_finance/app_routes.py
nexus_finance/investment_fitness.py
nexus_finance/investment_simulation.py
nexus_finance/investment_strategy.py
nexus_finance/main.py
nexus_finance/user_base.py
nexus_finance/user_type.py
nexus_finance/static/asset-manifest.json
nexus_finance/static/favicon.ico
nexus_finance/static/genetics-compose.png
nexus_finance/static/genetics.png
nexus_finance/static/genetics_split.png
nexus_finance/static/index.html
nexus_finance/static/logo192.png
nexus_finance/static/logo512.png
nexus_finance/static/manifest.json
nexus_finance/static/robots.txt
nexus_finance/static/static/css/main.684ed94d.css
nexus_finance/static/static/css/main.684ed94d.css.map
nexus_finance/static/static/js/453.6edf89f4.chunk.js
nexus_finance/static/static/js/453.6edf89f4.chunk.js.map
nexus_finance/static/static/js/main.01b59bf4.js
nexus_finance/static/static/js/main.01b59bf4.js.LICENSE.txt
nexus_finance/static/static/js/main.01b59bf4.js.map
nexus_finance/static/static/js/main.a772ad72.js
nexus_finance/static/static/js/main.a772ad72.js.LICENSE.txt
nexus_finance/static/static/js/main.a772ad72.js.map
nexus_finance/static/static/media/genetics-compose.a72f8b774aa5e8599a31.png
nexus_finance/static/static/media/genetics.2249fedc0035ab031014.png
nexus_finance-0.1.1.dist-info/LICENSE.txt
nexus_finance-0.1.1.dist-info/METADATA
nexus_finance-0.1.1.dist-info/WHEEL
nexus_finance-0.1.1.dist-info/top_level.txt
nexus_finance-0.1.1.dist-info/RECORD
