Metadata-Version: 2.2
Name: nexus_finance
Version: 0.1.1
Summary: Simulation for UserBase growth and financial forecast
Author-email: Henrik Lorenzen <h.lorenzen@nxs.solutions>
Project-URL: Homepage, https://github.com/nxs-solutions/NexusFinance.git
Classifier: Programming Language :: Python :: 3
Classifier: License :: OSI Approved :: MIT License
Classifier: Operating System :: OS Independent
Requires-Python: >=3.6
License-File: LICENSE.txt
Requires-Dist: Flask
Requires-Dist: deap
